CHANGELOG.md
CODE_OF_CONDUCT.md
CONTRIBUTING.md
README.md
slickml/__init__.py
slickml/base/__init__.py
slickml/base/_enum.py
slickml/base/_estimator.py
slickml/base/_metrics.py
slickml/beta/__init__.py
slickml/classification/__init__.py
slickml/classification/_glmnet.py
slickml/classification/_xgboost.py
slickml/classification/_xgboostcv.py
slickml/cli/__init__.py
slickml/cli/_cli.py
slickml/metrics/__init__.py
slickml/metrics/_classification.py
slickml/metrics/_regression.py
slickml/optimization/__init__.py
slickml/optimization/_bayesianopt.py
slickml/optimization/_hyperopt.py
slickml/py.typed
slickml/regression/__init__.py
slickml/regression/_glmnet.py
slickml/regression/_xgboost.py
slickml/regression/_xgboostcv.py
slickml/selection/__init__.py
slickml/selection/_xgboost.py
slickml/utils/__init__.py
slickml/utils/_annotations.py
slickml/utils/_format.py
slickml/utils/_transform.py
slickml/utils/_validation.py
slickml/visualization/__init__.py
slickml/visualization/_glmnet.py
slickml/visualization/_metrics.py
slickml/visualization/_selection.py
slickml/visualization/_shap.py
slickml/visualization/_xgboost.py
slickml-0.3.1.dist-info/LICENSE
slickml-0.3.1.dist-info/METADATA
slickml-0.3.1.dist-info/WHEEL
slickml-0.3.1.dist-info/entry_points.txt
slickml-0.3.1.dist-info/RECORD
