Metadata-Version: 2.1
Name: slickml
Version: 0.3.1
Summary: SlickML: Slick Machine Learning in Python
Home-page: https://www.slickml.com
License: MIT
Keywords: python,data-science,machine-learning
Author: Amirhessam Tahmassebi
Author-email: admin@slickml.com
Maintainer: Amirhessam Tahmassebi
Maintainer-email: admin@slickml.com
Requires-Python: >=3.9,<3.13
Classifier: Development Status :: 5 - Production/Stable
Classifier: Intended Audience :: Developers
Classifier: Intended Audience :: Science/Research
Classifier: License :: OSI Approved :: MIT License
Classifier: Natural Language :: English
Classifier: Operating System :: OS Independent
Classifier: Programming Language :: Python :: 3
Classifier: Programming Language :: Python :: 3.9
Classifier: Programming Language :: Python :: 3.10
Classifier: Programming Language :: Python :: 3.11
Classifier: Programming Language :: Python :: 3.12
Classifier: Programming Language :: Python :: 3 :: Only
Classifier: Topic :: Software Development :: Libraries :: Python Modules
Classifier: Typing :: Typed
Requires-Dist: bayesian-optimization (>=1.2)
Requires-Dist: click (>=8.1)
Requires-Dist: hyperopt (>=0.2)
Requires-Dist: matplotlib (>=3.5)
Requires-Dist: numpy (>=1.22,<2.0)
Requires-Dist: pandas (>=1.4,<2.0)
Requires-Dist: python-glmnet (>=2.2)
Requires-Dist: scikit-learn (>=1.5)
Requires-Dist: scipy (>=1.9)
Requires-Dist: seaborn (>=0.12)
Requires-Dist: shap (>=0.46)
Requires-Dist: statsmodels (>=0.13)
Requires-Dist: xgboost (>=1.7,<2.0)
Project-URL: Documentation, https://www.docs.slickml.com
Project-URL: Repository, https://github.com/slickml/slick-ml
